Workbook

Sheet PRODUITS
A1: DOCUMENT SYNTHETIQUE DE L'EXECUTION DU BUDGET 2020
A2: TABLEAU 1: PRODUITS
A3: SECTIONS | B3: N° DE COMPTE | C3: LIBELLES | D3: PREVISIONS INTIALES | E3: REALISATIONS AU 27/11/2020 | F3: RESTES A REALISER OU ECARTS | G3: TAUX DE REALISATION
A4: FONCTIONNEMENTS | B4: 70 | C4: VENTES
B5: 71 | C5: SUBVENTION D'EXPLOITATION
B6: 7181 | C6: SUBVENTION ETAT DU SENEGAL
B7: 75 | C7: AUTRES PRODUITS
C8: REPORT DE FONCTIONNEMENT 2019
B9: 799 | C9: REPRISES DE SUBVENTION D'INVESTISSEMENT
B10: TOTAL
A11: INVESTISSEMENTS | B11: 141 | C11: SUBVENTION D'INVESTISSEMENT
C23: REPORT D'INVESTISSEMENT 2019
B24: TOTAL
A25: TOTAL GENERAL

Sheet CHARGES
A3: DOCUMENT SYNTHETIQUE DE L'EXECUTION DU BUDGET 2020
A4: TABLEAU 2: CHARGES
A5: SECTIONS | B5: N° DE COMPTE | C5: LIBELLES | D5: PREVISIONS INITIALES | E5: ENGAGEMENTS AU 27/11/2020 | F5: ORDONNANCEMENTS AU 27/11/2020 | G5: MONTANTS PAYES AU 27/11/2020 | H5: DEPASSEMENT
A6: FONCTIONNEMENTS | B6: 60 | C6: Achats
B7: 61 | C7: Transport
B8: 62 | C8: Services Exterieurs
B9: 63 | C9: Autres Services Extérieurs
B10: 64 | C10: Impôts et Taxes
B11: 65 | C11: Autres Charges
B12: 66 | C12: Charges du personnel
B13: 67 | C13: Charges Financières
B14: 68 | C14: Dotations aux Amortissements
B15: TOTAL
B16: 16 | C16: Emprunts et Dettes auprès des Etablissements de crédits
A17: INVESTISSEMENTS | B17: 23 | C17: Bâtiments, Installations techniques et Agencements
B18: 24 | C18: Materiel immobilisé
B19: 275 | C19: Dépôt et Cautionnement
B20: TOTAL
A21: TOTAL GENERAL

Sheet INVEST, LT
B6: COMPTE ADMINISTRATIF DU 01 JANVIER AU 31 DECEMBRE 2019 AU TITRE DE L'EXERCICE 2019
B7: TABLEAU 3: SITUATION DES AUTORISATIONS DE PROGRAMMES (DEPENSES D'INVESTISSEMENTS A REALISER)
B9: LIBELLES DES PROGRAMME | C9: DATE DEBUT | D9: DATE FIN | E9: AUTORISATIONS D'ENGAGEMENT | H9: CREDITS DE PAIEMENT | K9: ORDONNANCEMENTS | N9: DISPONIBLES
E10: MONTANT INITIAL | F10: MODIFICATIONS | G10: TOTAL AP | H10: CUMUL CP ANTERIEURES | I10: CP DE L'ANNEE | J10: TOTAL | K10: CUMUL ORD GESTION ANTERIEURE | L10: ORD GESTION COURANTE | M10: TOTAL | N10: CP DISPONIBLES | O10: RESTES A PROGRAMMER
B17: TOTAL

Sheet RESULTAT
C4: DOCUMENT SYNTHETIQUE DE L'EXECUTION DU BUDGET 2020
C5: TABLEAU 3: RESULTAT DE GESTION
C7: SECTIONS | D7: PRODUITS | F7: CHARGES
D8: LIBELLE | E8: MONTANT | F8: LIBELLE | G8: MONTANT
C9: FONCTIONNEMENT | D9: VENTES | E9: =+PRODUITS!E4 -> 0 | F9: Achats | G9: =+CHARGES!G6 -> 0
D10: SUBVENTION D'EXPLOITATION | E10: =+PRODUITS!E5 -> 0 | F10: Transport | G10: =+CHARGES!G7 -> 0
D11: AUTRES PRODUITS | E11: =+PRODUITS!E7 -> 0 | F11: Services Exterieurs | G11: =+CHARGES!G8 -> 0
D12: REPRISE DOTATION AUX AMORTISSEMENTS | E12: 0 | F12: Autres Services | G12: =+CHARGES!G9 -> 0
D13: REPORT DE FONCTIONNEMENT 2019 | E13: 0 | F13: Impots et Taxes | G13: 0
F14: Autres Charges | G14: =+CHARGES!G11 -> 0
F15: Charges du personnel | G15: =+CHARGES!G12 -> 0
F16: Charges Financieres | G16: 0
F17: Dotation aux Amortissements | G17: 0
D18: TOTAL(1) | E18: =SUM(E9:E17) -> 0 | F18: TOTAL(3) | G18: =SUM(G9:G17) -> 0
D19: SOLDE DE LA SECTION DE FONCTIONNEMENT =
C20: INVESTISSEMENT | D20: =PRODUITS!C11 -> SUBVENTION D'INVESTISSEMENT | E20: =PRODUITS!E11 -> 0 | F20: Emprunts et Dettes auprès des Etablissements de crédits | G20: 0
F21: Batiments, Installations techniques et Agencements | G21: =+CHARGES!G17 -> 0
D22: =PRODUITS!C23 -> REPORT D'INVESTISSEMENT 2019 | E22: =PRODUITS!D23 -> 0 | F22: Materiel immobilisé | G22: =+CHARGES!G18 -> 0
D23: TOTAL(2) | E23: =E20+E22 -> 0 | F23: TOTAL(4) | G23: =G20+G21+G22 -> 0
D24: SOLDE DE LA SECTION D'INVESTISSEMENT =
C25: TOTAL GENERAL | E25: =E18+E23 -> 0 | F25: TOTAL GENERAL | G25: =G18+G23 -> 0
C26: SOLDE GLOBAL DE GESTION OU TOTAL REPORT A NOUVEAU =
